SOAPy_st/__init__.py
SOAPy_st/_compat.py
SOAPy_st/_docs.py
SOAPy_st/_metadata.py
SOAPy_st/_settings.py
SOAPy_st/utils.py
SOAPy_st/pl/__init__.py
SOAPy_st/pl/_ccc.py
SOAPy_st/pl/_chord.py
SOAPy_st/pl/_color.py
SOAPy_st/pl/_heatmap.py
SOAPy_st/pl/_neighborhood.py
SOAPy_st/pl/_niche.py
SOAPy_st/pl/_show.py
SOAPy_st/pl/_tendency.py
SOAPy_st/pl/_tensor.py
SOAPy_st/pl/utils.py
SOAPy_st/pp/__init__.py
SOAPy_st/pp/all2adata.py
SOAPy_st/pp/build_network.py
SOAPy_st/pp/utils.py
SOAPy_st/tl/__init__.py
SOAPy_st/tl/_ccc.py
SOAPy_st/tl/_domain.py
SOAPy_st/tl/_interaction.py
SOAPy_st/tl/_mask.py
SOAPy_st/tl/_tendency.py
SOAPy_st/tl/_tensor.py
SOAPy_st/tl/_var_genes.py
SOAPy_st/tl/utils.py
SOAPy_st/tl/datasets/Human-2020-Jin-LR-pairs.csv
SOAPy_st/tl/datasets/Mouse-2020-Jin-LR-pairs.csv
SOAPy_st/tl/other_package_without_pip/__init__.py
SOAPy_st/tl/other_package_without_pip/GraphST/GraphST.py
SOAPy_st/tl/other_package_without_pip/GraphST/__init__.py
SOAPy_st/tl/other_package_without_pip/GraphST/model.py
SOAPy_st/tl/other_package_without_pip/GraphST/preprocess.py
SOAPy_st/tl/other_package_without_pip/GraphST/utils.py
SOAPy_st/tl/other_package_without_pip/STAGATE_pyG/STAGATE.py
SOAPy_st/tl/other_package_without_pip/STAGATE_pyG/Train_STAGATE.py
SOAPy_st/tl/other_package_without_pip/STAGATE_pyG/__init__.py
SOAPy_st/tl/other_package_without_pip/STAGATE_pyG/gat_conv.py
SOAPy_st/tl/other_package_without_pip/STAGATE_pyG/utils.py
SOAPy_st/tl/other_package_without_pip/scanit/__init__.py
SOAPy_st/tl/other_package_without_pip/scanit/_utils/__init__.py
SOAPy_st/tl/other_package_without_pip/scanit/_utils/_alpha.py
SOAPy_st/tl/other_package_without_pip/scanit/_utils/_dgi.py
SOAPy_st/tl/other_package_without_pip/scanit/_utils/_gae.py
SOAPy_st/tl/other_package_without_pip/scanit/_utils/_knn.py
SOAPy_st/tl/other_package_without_pip/scanit/_utils/_scale_estimation.py
SOAPy_st/tl/other_package_without_pip/scanit/tools/__init__.py
SOAPy_st-1.0.1.dist-info/LICENSE.md
SOAPy_st-1.0.1.dist-info/METADATA
SOAPy_st-1.0.1.dist-info/WHEEL
SOAPy_st-1.0.1.dist-info/top_level.txt
SOAPy_st-1.0.1.dist-info/RECORD
