Metadata-Version: 2.1
Name: SOAPy-st
Version: 1.0.1
Summary: Spatial Omics Analysis in Python
Home-page: https://github.com/LiHongCSBLab/SOAPy
Author: Cancer system biology lab
Author-email: wangheqi2021@sinh.ac.cn
License: UNKNOWN
Keywords: bio-informatics,spatial data analysis,spatial omics,spatial transcriptomics
Platform: UNKNOWN
Classifier: Development Status :: 3 - Alpha
Classifier: Intended Audience :: Developers
Classifier: Natural Language :: English
Classifier: Programming Language :: Python :: 3
Requires-Python: >=3.9
License-File: LICENSE.md
Requires-Dist: anndata (==0.9.1)
Requires-Dist: ctxcore (==0.2.0)
Requires-Dist: esda (==2.4.3)
Requires-Dist: geopandas (==0.14.3)
Requires-Dist: libpysal (==4.8.1)
Requires-Dist: networkx (==2.8.6)
Requires-Dist: numba (==0.60.0)
Requires-Dist: opencv-python (==4.8.1.78)
Requires-Dist: pyscenic (==0.12.1)
Requires-Dist: s-dbw (==0.4.0)
Requires-Dist: shapely (==2.0.3)
Requires-Dist: scanpy (==1.10.3)
Requires-Dist: scikit-image (==0.19.3)
Requires-Dist: scikit-learn (==1.1.2)
Requires-Dist: scikit-misc (==0.3.1)
Requires-Dist: scipy (==1.13.1)
Requires-Dist: seaborn (==0.13.2)
Requires-Dist: statsmodels (==0.13.2)
Requires-Dist: tensorly (==0.8.1)
Requires-Dist: torch (==1.12.0)
Requires-Dist: torchaudio (==0.12.0)
Requires-Dist: torchvision (==0.13.0)
Requires-Dist: matplotlib
Requires-Dist: numpy
Requires-Dist: pandas
Requires-Dist: tqdm
